MPCdata/MPC_parser.py
MPCdata/__init__.py
MPCdata_Aplysia-0.0.2.1.dist-info/LICENSE
MPCdata_Aplysia-0.0.2.1.dist-info/METADATA
MPCdata_Aplysia-0.0.2.1.dist-info/WHEEL
MPCdata_Aplysia-0.0.2.1.dist-info/top_level.txt
MPCdata_Aplysia-0.0.2.1.dist-info/RECORD
