Metadata-Version: 2.1
Name: MPCdata-Aplysia
Version: 0.0.2.1
Summary: Package to read Med Associates Files MedPCIV
Home-page: https://github.com/matthewperkins/MPCdata
Author: Matthew Perkins
Author-email: matthew.perkins@mssm.edu
License: UNKNOWN
Platform: UNKNOWN
Classifier: Programming Language :: Python :: 3
Classifier: License :: OSI Approved :: MIT License
Classifier: Operating System :: OS Independent
